setup.py
pyssml/AmazonSpeech.py
pyssml/PySSML.py
pyssml/__init__.py
pyssml.egg-info/PKG-INFO
pyssml.egg-info/SOURCES.txt
pyssml.egg-info/dependency_links.txt
pyssml.egg-info/top_level.txt