Metadata-Version: 1.1
Name: pyssml
Version: 0.1.3
Summary: Python library for building SSML for Amazon Alexa
Home-page: https://github.com/sumsted/pyssml
Author: Scott Umsted
Author-email: scott@wildidea.xyz
License: Apache
Keywords: ssml python pyssml amazon alexa
Platform: UNKNOWN
Classifier: Development Status :: 5 - Production/Stable
Classifier: Intended Audience :: Developers
Classifier: Topic :: Software Development :: Libraries :: Python Modules
Classifier: License :: OSI Approved :: Apache Software License
Classifier: Programming Language :: Python :: 2.7
Classifier: Programming Language :: Python :: 3
Classifier: Programming Language :: Python :: 3.2
Classifier: Programming Language :: Python :: 3.3
Classifier: Programming Language :: Python :: 3.4
Classifier: Programming Language :: Python :: 3.5
